mcp_connection.py
mcp_server_init-0.1.1.dist-info/METADATA
mcp_server_init-0.1.1.dist-info/WHEEL
mcp_server_init-0.1.1.dist-info/top_level.txt
mcp_server_init-0.1.1.dist-info/RECORD
